zla_class/__init__.py
zla_class/master_sql.py
zla_class/multiple_gi.py
zla_class/multiple_rs.py
zla_class/multiple_ws.py
zla_class/rs_class.py
zla_class/rs_data_sql.py
zla_class/rs_method.py
zla_class/ws_class.py
zla_class/ws_data_sql.py
zla_class/ws_method.py
zla_class/common_tools/__init__.py
zla_class/common_tools/general_func.py
zla_class/common_tools/master_sql.py
zla_class/rs_tools/__init__.py
zla_class/rs_tools/multiple_rs_sql.py
zla_class/rs_tools/rs_data_sql.py
zla_class/rs_tools/rs_method.py
zla_class/ws_tools/__init__.py
zla_class/ws_tools/multiple_ws_sql.py
zla_class/ws_tools/ws_data_sql.py
zla_class/ws_tools/ws_method.py
zla_class-1.0.6.dist-info/LICENSE.txt
zla_class-1.0.6.dist-info/METADATA
zla_class-1.0.6.dist-info/WHEEL
zla_class-1.0.6.dist-info/top_level.txt
zla_class-1.0.6.dist-info/RECORD
