Metadata-Version: 2.1
Name: zla-class
Version: 1.0.6
Summary: zla_class for get wholesale and retails sale
Home-page: UNKNOWN
Author: zlakeaw
Author-email: zla.naratip@gmail.com
License: UNKNOWN
Platform: UNKNOWN
Classifier: Programming Language :: Python :: 3
Classifier: License :: OSI Approved :: MIT License
Classifier: Operating System :: OS Independent
Requires-Python: >=3.6
Requires-Dist: numpy
Requires-Dist: pandas
Requires-Dist: pyodbc
Requires-Dist: datetime
Requires-Dist: zla-utilities
Requires-Dist: zla-general
